wscribe/__init__.py
wscribe/backends/fasterwhisper.py
wscribe/cli/main.py
wscribe/core.py
wscribe/sources/local.py
wscribe/writers.py
wscribe-0.1.5.dist-info/LICENSE
wscribe-0.1.5.dist-info/METADATA
wscribe-0.1.5.dist-info/WHEEL
wscribe-0.1.5.dist-info/entry_points.txt
wscribe-0.1.5.dist-info/RECORD
