Metadata-Version: 2.1
Name: wscribe
Version: 0.1.5
Summary: ez audio transcription tool with flexible processing and post-processing options
Home-page: https://github.com/geekodour/wscribe
License: MIT
Author: Hrishikesh Barman
Author-email: oss@geekodour.org
Requires-Python: >=3.10,<4.0
Classifier: License :: OSI Approved :: MIT License
Classifier: Programming Language :: Python :: 3
Classifier: Programming Language :: Python :: 3.10
Classifier: Programming Language :: Python :: 3.11
Requires-Dist: click (>=8.1.6,<9.0.0)
Requires-Dist: faster-whisper (>=0.9.0,<0.10.0)
Requires-Dist: structlog (>=23.1.0,<24.0.0)
